{"segments": [{"text": "Slow German, der Podcast zum Deutsch lernen.", "start": 0.211, "end": 3.64, "no_speech_prob": 0}, {"text": "Mit Annik Rubens.", "start": 3.68, "end": 4.883, "no_speech_prob": 0}, {"text": "Heute erzähle ich Euch eine Geschichte, die vor langer Zeit begann.", "start": 6.783, "end": 13.648, "no_speech_prob": 0}, {"text": "1845 ging es den Menschen in Sachsen schlecht.", "start": 13.828, "end": 18.771, "no_speech_prob": 0}, {"text": "Vorher hatten sie vor allem vom Silber in der Region gelebt.", "start": 18.811, "end": 24.715, "no_speech_prob": 0}, {"text": "Aber es wurde immer weniger Silber gefunden.", "start": 24.775, "end": 29.378, "no_speech_prob": 0}, {"text": "Also hatte Ferdinand A.", "start": 29.418, "end": 31.68, "no_speech_prob": 0}, {"text": "Lange in der Stadt Glashütte eine Idee.", "start": 31.7, "end": 35.443, "no_speech_prob": 0}, {"text": "Er gründete ein Uhrenunternehmen.", "start": 36.483, "end": 40.387, "no_speech_prob": 0}, {"text": "Die Kunst der Uhrmacherei kannte er aus Frankreich, England und der Schweiz.", "start": 40.407, "end": 48.055, "no_speech_prob": 0}, {"text": "Die sächsische Landesregierung half ihm.", "start": 48.095, "end": 52.359, "no_speech_prob": 0}, {"text": "Sie ermöglichte den Bergarbeitern und Strohflechtern eine Ausbildung zum Uhrmacher.", "start": 52.399, "end": 60.326, "no_speech_prob": 0}, {"text": "Schon bald wurde der Ort Glashütte in Sachsen berühmt für seine edlen, hochwertigen und vor allem handgemachten Uhren.", "start": 61.467, "end": 74.519, "no_speech_prob": 0}, {"text": "So etwas kannte man sonst nur aus der Schweiz.", "start": 74.539, "end": 80.183, "no_speech_prob": 0}, {"text": "Glashütte wurde zu einer Uhrenstadt.", "start": 80.203, "end": 83.646, "no_speech_prob": 0}, {"text": "Während des Zweiten Weltkriegs mussten Uhrmacher auch Dinge herstellen, die für den Krieg wichtig waren, also bauten sie zum Beispiel Zeitzünder.", "start": 85.067, "end": 100.478, "no_speech_prob": 0}, {"text": "Nach dem Krieg wurden die Uhrenfirmen in Glashütte enteignet und verstaatlicht.", "start": 100.518, "end": 108.523, "no_speech_prob": 0}, {"text": "Sie gehörten also fortan dem Staat, denn in der DDR galt der Sozialismus.", "start": 109.744, "end": 119.348, "no_speech_prob": 0}, {"text": "Alle Betriebe, die in Ostdeutschland Uhren herstellten, wurden zu einem großen Betrieb zusammengefasst.", "start": 119.368, "end": 128.672, "no_speech_prob": 0}, {"text": "Dann kam 1990 die Wiedervereinigung und der staatliche Uhrenbetrieb wurde wieder in die freie Wirtschaft eingegliedert.", "start": 130.113, "end": 144.096, "no_speech_prob": 0}, {"text": "Verschiedene Firmen aus Glashütte stehen weiterhin für traditionelles Urhandwerk.", "start": 144.136, "end": 151.578, "no_speech_prob": 0}, {"text": "Mühle Glashütte ist eine Firma, die seit 1869 in Familienbesitz ist.", "start": 152.859, "end": 162.425, "no_speech_prob": 0}, {"text": "Gegründet wurde sie von Robert Mühle.", "start": 162.445, "end": 166.627, "no_speech_prob": 0}, {"text": "Er hatte in der Uhrmacher-Schule in Glashütte sein Handwerk gelernt.", "start": 166.667, "end": 172.911, "no_speech_prob": 0}, {"text": "Der Glashütter Uhrenbetrieb ist das, was vom DDR-Betrieb übrig blieb.", "start": 174.292, "end": 181.334, "no_speech_prob": 0}, {"text": "Die Arbeiter schlossen sich zusammen und begannen, die neu-alte Marke wiederherzustellen.", "start": 181.354, "end": 190.556, "no_speech_prob": 0}, {"text": "Sie bauten Uhren unter dem Markennamen Glashütte Original.", "start": 190.596, "end": 196.357, "no_speech_prob": 0}, {"text": "Und dann?", "start": 197.868, "end": 199.13, "no_speech_prob": 0}, {"text": "Dann wurde der Glashütter Uhrenbetrieb von dem Schweizer Unternehmen Swatch gekauft.", "start": 199.17, "end": 206.26, "no_speech_prob": 0}, {"text": "Nomos Glashütte wurde erst 1990 gegründet und dementsprechend modern sind auch die Uhren.", "start": 207.823, "end": 217.928, "no_speech_prob": 0}, {"text": "Und was wurde aus den A.", "start": 217.968, "end": 220.349, "no_speech_prob": 0}, {"text": "Lange & Söhne Uhren?", "start": 220.39, "end": 223.051, "no_speech_prob": 0}, {"text": "Sie gibt es heute wieder, nachdem es 1990 eine Neugründung der Marke gab.", "start": 223.071, "end": 230.835, "no_speech_prob": 0}, {"text": "Schön ist, dass die Uhren auch heute noch klassisch aussehen.", "start": 231.895, "end": 237.758, "no_speech_prob": 0}, {"text": "Natürlich wurden sie weiterentwickelt, aber es sind edle Uhren, die sich viele Männer in Deutschland wünschen.", "start": 237.798, "end": 248.163, "no_speech_prob": 0}, {"text": "Wenn Ihr mal nachschaut, werdet Ihr sehen, dass manche dieser Uhren 150.000 Euro kosten.", "start": 248.183, "end": 257.488, "no_speech_prob": 0}, {"text": "Würdet Ihr so viel Geld für eine Uhr ausgeben?", "start": 259.393, "end": 264.817, "no_speech_prob": 0}, {"text": "Viele Menschen tun das, denn eine Uhr ist und bleibt ein Statussymbol.", "start": 264.837, "end": 272.101, "no_speech_prob": 0}, {"text": "Ob es die berühmte Rolex ist oder eine Glashütte-Uhr, das könnte viel über den Träger aussagen, oder?", "start": 272.161, "end": 282.087, "no_speech_prob": 0}, {"text": "Egal wie teuer eine Uhr aber ist, eines kann sie nicht.", "start": 283.608, "end": 288.913, "no_speech_prob": 0}, {"text": "Sie kann uns nicht mehr Zeit verschaffen für all die Dinge, die wir noch gerne in unserem Leben tun würden.", "start": 288.953, "end": 296.681, "no_speech_prob": 0}], "words": [{"word": "Slow", "start": 0.211, "end": 0.492}, {"word": "German,", "start": 0.552, "end": 1.394}, {"word": "der", "start": 1.415, "end": 1.635}, {"word": "Podcast", "start": 1.655, "end": 2.297}, {"word": "zum", "start": 2.317, "end": 2.517}, {"word": "Deutsch", "start": 2.557, "end": 2.858}, {"word": "lernen.", "start": 2.878, "end": 3.64}, {"word": "Mit", "start": 3.68, "end": 4.001}, {"word": "Annik", "start": 4.081, "end": 4.402}, {"word": "Rubens.", "start": 4.482, "end": 4.883}, {"word": "Heute", "start": 6.783, "end": 7.204}, {"word": "erzähle", "start": 7.264, "end": 7.864}, {"word": "ich", "start": 7.904, "end": 8.064}, {"word": "Euch", "start": 8.124, "end": 8.524}, {"word": "eine", "start": 8.544, "end": 8.825}, {"word": "Geschichte,", "start": 8.845, "end": 9.765}, {"word": "die", "start": 9.785, "end": 10.005}, {"word": "vor", "start": 10.025, "end": 10.246}, {"word": "langer", "start": 10.286, "end": 10.726}, {"word": "Zeit", "start": 10.766, "end": 11.246}, {"word": "begann.", "start": 11.266, "end": 13.648}, {"word": "1845", "start": 13.828, "end": 15.129}, {"word": "ging", "start": 15.169, "end": 15.309}, {"word": "es", "start": 15.349, "end": 15.569}, {"word": "den", "start": 15.589, "end": 15.789}, {"word": "Menschen", "start": 15.829, "end": 16.45}, {"word": "in", "start": 16.51, "end": 16.67}, {"word": "Sachsen", "start": 16.71, "end": 17.25}, {"word": "schlecht.", "start": 17.29, "end": 18.771}, {"word": "Vorher", "start": 18.811, "end": 19.392}, {"word": "hatten", "start": 19.432, "end": 19.852}, {"word": "sie", "start": 19.892, "end": 20.192}, {"word": "vor", "start": 20.232, "end": 20.553}, {"word": "allem", "start": 20.593, "end": 21.113}, {"word": "vom", "start": 21.153, "end": 21.493}, {"word": "Silber", "start": 21.533, "end": 22.234}, {"word": "in", "start": 22.274, "end": 22.434}, {"word": "der", "start": 22.474, "end": 22.714}, {"word": "Region", "start": 22.734, "end": 23.334}, {"word": "gelebt.", "start": 23.374, "end": 24.715}, {"word": "Aber", "start": 24.775, "end": 25.156}, {"word": "es", "start": 25.216, "end": 25.416}, {"word": "wurde", "start": 25.476, "end": 25.976}, {"word": "immer", "start": 26.016, "end": 26.537}, {"word": "weniger", "start": 26.597, "end": 27.177}, {"word": "Silber", "start": 27.237, "end": 27.837}, {"word": "gefunden.", "start": 27.877, "end": 29.378}, {"word": "Also", "start": 29.418, "end": 29.919}, {"word": "hatte", "start": 29.959, "end": 30.459}, {"word": "Ferdinand", "start": 30.499, "end": 31.3}, {"word": "A.", "start": 31.36, "end": 31.68}, {"word": "Lange", "start": 31.7, "end": 32.581}, {"word": "in", "start": 32.621, "end": 32.761}, {"word": "der", "start": 32.801, "end": 32.981}, {"word": "Stadt", "start": 33.041, "end": 33.561}, {"word": "Glashütte", "start": 33.601, "end": 34.802}, {"word": "eine", "start": 34.862, "end": 35.122}, {"word": "Idee.", "start": 35.182, "end": 35.443}, {"word": "Er", "start": 36.483, "end": 36.643}, {"word": "gründete", "start": 36.704, "end": 37.644}, {"word": "ein", "start": 37.684, "end": 38.005}, {"word": "Uhrenunternehmen.", "start": 38.105, "end": 40.387}, {"word": "Die", "start": 40.407, "end": 40.607}, {"word": "Kunst", "start": 40.647, "end": 41.128}, {"word": "der", "start": 41.168, "end": 41.428}, {"word": "Uhrmacherei", "start": 41.468, "end": 42.769}, {"word": "kannte", "start": 42.809, "end": 43.23}, {"word": "er", "start": 43.27, "end": 43.57}, {"word": "aus", "start": 43.61, "end": 43.87}, {"word": "Frankreich,", "start": 43.931, "end": 44.871}, {"word": "England", "start": 44.931, "end": 45.692}, {"word": "und", "start": 45.732, "end": 46.273}, {"word": "der", "start": 46.313, "end": 46.473}, {"word": "Schweiz.", "start": 46.513, "end": 48.055}, {"word": "Die", "start": 48.095, "end": 48.335}, {"word": "sächsische", "start": 48.375, "end": 49.176}, {"word": "Landesregierung", "start": 49.216, "end": 50.677}, {"word": "half", "start": 50.737, "end": 51.178}, {"word": "ihm.", "start": 51.238, "end": 52.359}, {"word": "Sie", "start": 52.399, "end": 52.659}, {"word": "ermöglichte", "start": 52.719, "end": 53.76}, {"word": "den", "start": 53.78, "end": 54.08}, {"word": "Bergarbeitern", "start": 54.12, "end": 55.382}, {"word": "und", "start": 55.422, "end": 55.762}, {"word": "Strohflechtern", "start": 55.822, "end": 57.484}, {"word": "eine", "start": 57.524, "end": 57.924}, {"word": "Ausbildung", "start": 57.984, "end": 59.045}, {"word": "zum", "start": 59.085, "end": 59.586}, {"word": "Uhrmacher.", "start": 59.666, "end": 60.326}, {"word": "Schon", "start": 61.467, "end": 61.708}, {"word": "bald", "start": 61.768, "end": 62.308}, {"word": "wurde", "start": 62.348, "end": 62.708}, {"word": "der", "start": 62.749, "end": 63.049}, {"word": "Ort", "start": 63.149, "end": 63.749}, {"word": "Glashütte", "start": 63.789, "end": 64.97}, {"word": "in", "start": 65.03, "end": 65.291}, {"word": "Sachsen", "start": 65.351, "end": 66.091}, {"word": "berühmt", "start": 66.131, "end": 66.952}, {"word": "für", "start": 66.992, "end": 67.312}, {"word": "seine", "start": 67.352, "end": 67.873}, {"word": "edlen,", "start": 67.993, "end": 69.054}, {"word": "hochwertigen", "start": 69.094, "end": 70.495}, {"word": "und", "start": 70.535, "end": 70.795}, {"word": "vor", "start": 70.815, "end": 71.016}, {"word": "allem", "start": 71.056, "end": 71.656}, {"word": "handgemachten", "start": 71.696, "end": 73.057}, {"word": "Uhren.", "start": 73.137, "end": 74.519}, {"word": "So", "start": 74.539, "end": 74.799}, {"word": "etwas", "start": 74.839, "end": 75.499}, {"word": "kannte", "start": 75.539, "end": 76.1}, {"word": "man", "start": 76.12, "end": 76.5}, {"word": "sonst", "start": 76.54, "end": 77.501}, {"word": "nur", "start": 77.521, "end": 77.921}, {"word": "aus", "start": 77.961, "end": 78.242}, {"word": "der", "start": 78.262, "end": 78.482}, {"word": "Schweiz.", "start": 78.522, "end": 80.183}, {"word": "Glashütte", "start": 80.203, "end": 81.264}, {"word": "wurde", "start": 81.324, "end": 81.845}, {"word": "zu", "start": 81.885, "end": 82.205}, {"word": "einer", "start": 82.245, "end": 82.685}, {"word": "Uhrenstadt.", "start": 82.806, "end": 83.646}, {"word": "Während", "start": 85.067, "end": 85.628}, {"word": "des", "start": 85.668, "end": 86.068}, {"word": "Zweiten", "start": 86.108, "end": 86.709}, {"word": "Weltkriegs", "start": 86.749, "end": 88.009}, {"word": "mussten", "start": 88.049, "end": 88.75}, {"word": "Uhrmacher", "start": 88.81, "end": 89.751}, {"word": "auch", "start": 89.811, "end": 90.191}, {"word": "Dinge", "start": 90.231, "end": 90.691}, {"word": "herstellen,", "start": 90.731, "end": 91.952}, {"word": "die", "start": 91.972, "end": 92.232}, {"word": "für", "start": 92.252, "end": 92.492}, {"word": "den", "start": 92.532, "end": 92.833}, {"word": "Krieg", "start": 92.873, "end": 93.493}, {"word": "wichtig", "start": 93.533, "end": 94.074}, {"word": "waren,", "start": 94.114, "end": 95.254}, {"word": "also", "start": 95.314, "end": 95.835}, {"word": "bauten", "start": 95.875, "end": 96.475}, {"word": "sie", "start": 96.515, "end": 96.976}, {"word": "zum", "start": 97.036, "end": 97.296}, {"word": "Beispiel", "start": 97.336, "end": 98.236}, {"word": "Zeitzünder.", "start": 98.276, "end": 100.478}, {"word": "Nach", "start": 100.518, "end": 100.818}, {"word": "dem", "start": 100.838, "end": 101.158}, {"word": "Krieg", "start": 101.198, "end": 101.999}, {"word": "wurden", "start": 102.059, "end": 102.619}, {"word": "die", "start": 102.659, "end": 102.94}, {"word": "Uhrenfirmen", "start": 103.04, "end": 104.321}, {"word": "in", "start": 104.361, "end": 104.621}, {"word": "Glashütte", "start": 104.681, "end": 106.002}, {"word": "enteignet", "start": 106.042, "end": 107.102}, {"word": "und", "start": 107.142, "end": 107.643}, {"word": "verstaatlicht.", "start": 107.683, "end": 108.523}, {"word": "Sie", "start": 109.744, "end": 109.984}, {"word": "gehörten", "start": 110.024, "end": 110.925}, {"word": "also", "start": 110.985, "end": 111.465}, {"word": "fortan", "start": 111.545, "end": 112.385}, {"word": "dem", "start": 112.425, "end": 112.665}, {"word": "Staat,", "start": 112.705, "end": 113.906}, {"word": "denn", "start": 113.926, "end": 114.346}, {"word": "in", "start": 114.386, "end": 114.646}, {"word": "der", "start": 114.666, "end": 114.946}, {"word": "DDR", "start": 114.986, "end": 116.247}, {"word": "galt", "start": 116.307, "end": 116.867}, {"word": "der", "start": 116.887, "end": 117.187}, {"word": "Sozialismus.", "start": 117.227, "end": 119.348}, {"word": "Alle", "start": 119.368, "end": 119.769}, {"word": "Betriebe,", "start": 119.829, "end": 120.889}, {"word": "die", "start": 120.909, "end": 121.149}, {"word": "in", "start": 121.189, "end": 121.469}, {"word": "Ostdeutschland", "start": 121.529, "end": 122.77}, {"word": "Uhren", "start": 122.87, "end": 123.33}, {"word": "herstellten,", "start": 123.37, "end": 124.531}, {"word": "wurden", "start": 124.591, "end": 125.191}, {"word": "zu", "start": 125.231, "end": 125.531}, {"word": "einem", "start": 125.591, "end": 126.031}, {"word": "großen", "start": 126.071, "end": 126.692}, {"word": "Betrieb", "start": 126.732, "end": 127.412}, {"word": "zusammengefasst.", "start": 127.452, "end": 128.672}, {"word": "Dann", "start": 130.113, "end": 130.553}, {"word": "kam", "start": 130.613, "end": 131.093}, {"word": "1990", "start": 131.393, "end": 133.394}, {"word": "die", "start": 133.414, "end": 133.734}, {"word": "Wiedervereinigung", "start": 133.774, "end": 135.714}, {"word": "und", "start": 135.754, "end": 136.194}, {"word": "der", "start": 136.214, "end": 136.434}, {"word": "staatliche", "start": 136.495, "end": 137.355}, {"word": "Uhrenbetrieb", "start": 137.455, "end": 138.875}, {"word": "wurde", "start": 138.915, "end": 139.415}, {"word": "wieder", "start": 139.435, "end": 140.055}, {"word": "in", "start": 140.095, "end": 140.295}, {"word": "die", "start": 140.335, "end": 140.555}, {"word": "freie", "start": 140.615, "end": 141.116}, {"word": "Wirtschaft", "start": 141.156, "end": 142.096}, {"word": "eingegliedert.", "start": 142.136, "end": 144.096}, {"word": "Verschiedene", "start": 144.136, "end": 144.936}, {"word": "Firmen", "start": 144.996, "end": 145.697}, {"word": "aus", "start": 145.757, "end": 146.057}, {"word": "Glashütte", "start": 146.117, "end": 147.357}, {"word": "stehen", "start": 147.397, "end": 147.917}, {"word": "weiterhin", "start": 147.957, "end": 149.017}, {"word": "für", "start": 149.057, "end": 149.357}, {"word": "traditionelles", "start": 149.397, "end": 150.658}, {"word": "Urhandwerk.", "start": 150.718, "end": 151.578}, {"word": "Mühle", "start": 152.859, "end": 153.339}, {"word": "Glashütte", "start": 153.379, "end": 154.36}, {"word": "ist", "start": 154.42, "end": 154.76}, {"word": "eine", "start": 154.8, "end": 155.1}, {"word": "Firma,", "start": 155.14, "end": 156.041}, {"word": "die", "start": 156.061, "end": 156.301}, {"word": "seit", "start": 156.341, "end": 156.741}, {"word": "1869", "start": 157.942, "end": 159.423}, {"word": "in", "start": 159.463, "end": 159.763}, {"word": "Familienbesitz", "start": 159.803, "end": 161.084}, {"word": "ist.", "start": 161.144, "end": 162.425}, {"word": "Gegründet", "start": 162.445, "end": 163.225}, {"word": "wurde", "start": 163.265, "end": 163.645}, {"word": "sie", "start": 163.685, "end": 164.126}, {"word": "von", "start": 164.166, "end": 164.546}, {"word": "Robert", "start": 164.606, "end": 165.246}, {"word": "Mühle.", "start": 165.286, "end": 166.627}, {"word": "Er", "start": 166.667, "end": 166.867}, {"word": "hatte", "start": 166.888, "end": 167.488}, {"word": "in", "start": 167.548, "end": 167.848}, {"word": "der", "start": 167.888, "end": 168.208}, {"word": "Uhrmacher-Schule", "start": 168.268, "end": 169.789}, {"word": "in", "start": 169.829, "end": 170.049}, {"word": "Glashütte", "start": 170.09, "end": 171.27}, {"word": "sein", "start": 171.31, "end": 171.61}, {"word": "Handwerk", "start": 171.651, "end": 172.451}, {"word": "gelernt.", "start": 172.491, "end": 172.911}, {"word": "Der", "start": 174.292, "end": 174.512}, {"word": "Glashütter", "start": 174.552, "end": 175.312}, {"word": "Uhrenbetrieb", "start": 175.392, "end": 176.613}, {"word": "ist", "start": 176.653, "end": 176.913}, {"word": "das,", "start": 176.953, "end": 177.653}, {"word": "was", "start": 177.693, "end": 177.933}, {"word": "vom", "start": 177.953, "end": 178.273}, {"word": "DDR-Betrieb", "start": 178.313, "end": 179.713}, {"word": "übrig", "start": 179.753, "end": 180.153}, {"word": "blieb.", "start": 180.193, "end": 181.334}, {"word": "Die", "start": 181.354, "end": 181.594}, {"word": "Arbeiter", "start": 181.654, "end": 182.414}, {"word": "schlossen", "start": 182.514, "end": 183.194}, {"word": "sich", "start": 183.234, "end": 183.594}, {"word": "zusammen", "start": 183.634, "end": 184.734}, {"word": "und", "start": 184.774, "end": 185.114}, {"word": "begannen,", "start": 185.154, "end": 186.135}, {"word": "die", "start": 186.155, "end": 186.495}, {"word": "neu-alte", "start": 186.555, "end": 187.435}, {"word": "Marke", "start": 187.455, "end": 188.255}, {"word": "wiederherzustellen.", "start": 188.295, "end": 190.556}, {"word": "Sie", "start": 190.596, "end": 190.856}, {"word": "bauten", "start": 190.896, "end": 191.456}, {"word": "Uhren", "start": 191.556, "end": 192.236}, {"word": "unter", "start": 192.276, "end": 192.896}, {"word": "dem", "start": 192.916, "end": 193.216}, {"word": "Markennamen", "start": 193.256, "end": 194.637}, {"word": "Glashütte", "start": 194.677, "end": 195.597}, {"word": "Original.", "start": 195.677, "end": 196.357}, {"word": "Und", "start": 197.868, "end": 198.069}, {"word": "dann?", "start": 198.109, "end": 199.13}, {"word": "Dann", "start": 199.17, "end": 199.49}, {"word": "wurde", "start": 199.531, "end": 200.011}, {"word": "der", "start": 200.051, "end": 200.332}, {"word": "Glashütter", "start": 200.372, "end": 201.233}, {"word": "Uhrenbetrieb", "start": 201.313, "end": 202.695}, {"word": "von", "start": 202.735, "end": 202.935}, {"word": "dem", "start": 202.955, "end": 203.175}, {"word": "Schweizer", "start": 203.216, "end": 203.917}, {"word": "Unternehmen", "start": 203.997, "end": 204.998}, {"word": "Swatch", "start": 205.038, "end": 205.799}, {"word": "gekauft.", "start": 205.819, "end": 206.26}, {"word": "Nomos", "start": 207.823, "end": 208.383}, {"word": "Glashütte", "start": 208.423, "end": 209.424}, {"word": "wurde", "start": 209.484, "end": 209.924}, {"word": "erst", "start": 209.964, "end": 210.224}, {"word": "1990", "start": 210.505, "end": 211.965}, {"word": "gegründet", "start": 212.005, "end": 213.046}, {"word": "und", "start": 213.086, "end": 213.366}, {"word": "dementsprechend", "start": 213.406, "end": 214.446}, {"word": "modern", "start": 214.487, "end": 215.307}, {"word": "sind", "start": 215.347, "end": 215.627}, {"word": "auch", "start": 215.667, "end": 216.147}, {"word": "die", "start": 216.167, "end": 216.327}, {"word": "Uhren.", "start": 216.428, "end": 217.928}, {"word": "Und", "start": 217.968, "end": 218.288}, {"word": "was", "start": 218.348, "end": 218.709}, {"word": "wurde", "start": 218.749, "end": 219.269}, {"word": "aus", "start": 219.309, "end": 219.549}, {"word": "den", "start": 219.569, "end": 219.889}, {"word": "A.", "start": 219.969, "end": 220.349}, {"word": "Lange", "start": 220.39, "end": 220.83}, {"word": "&", "start": 220.87, "end": 221.13}, {"word": "Söhne", "start": 221.17, "end": 221.63}, {"word": "Uhren?", "start": 221.69, "end": 223.051}, {"word": "Sie", "start": 223.071, "end": 223.351}, {"word": "gibt", "start": 223.371, "end": 223.671}, {"word": "es", "start": 223.731, "end": 223.951}, {"word": "heute", "start": 223.991, "end": 224.412}, {"word": "wieder,", "start": 224.452, "end": 225.232}, {"word": "nachdem", "start": 225.252, "end": 225.772}, {"word": "es", "start": 225.812, "end": 226.032}, {"word": "1990", "start": 226.292, "end": 228.173}, {"word": "eine", "start": 228.233, "end": 228.614}, {"word": "Neugründung", "start": 228.654, "end": 229.714}, {"word": "der", "start": 229.734, "end": 229.934}, {"word": "Marke", "start": 229.994, "end": 230.415}, {"word": "gab.", "start": 230.455, "end": 230.835}, {"word": "Schön", "start": 231.895, "end": 232.296}, {"word": "ist,", "start": 232.356, "end": 232.816}, {"word": "dass", "start": 232.856, "end": 233.196}, {"word": "die", "start": 233.236, "end": 233.396}, {"word": "Uhren", "start": 233.496, "end": 234.036}, {"word": "auch", "start": 234.076, "end": 234.397}, {"word": "heute", "start": 234.437, "end": 234.857}, {"word": "noch", "start": 234.897, "end": 235.477}, {"word": "klassisch", "start": 235.517, "end": 236.277}, {"word": "aussehen.", "start": 236.338, "end": 237.758}, {"word": "Natürlich", "start": 237.798, "end": 238.659}, {"word": "wurden", "start": 238.719, "end": 239.139}, {"word": "sie", "start": 239.159, "end": 239.559}, {"word": "weiterentwickelt,", "start": 239.599, "end": 241.32}, {"word": "aber", "start": 241.36, "end": 241.84}, {"word": "es", "start": 241.9, "end": 242.1}, {"word": "sind", "start": 242.14, "end": 242.501}, {"word": "edle", "start": 242.561, "end": 243.041}, {"word": "Uhren,", "start": 243.181, "end": 244.041}, {"word": "die", "start": 244.061, "end": 244.241}, {"word": "sich", "start": 244.281, "end": 244.602}, {"word": "viele", "start": 244.642, "end": 245.042}, {"word": "Männer", "start": 245.102, "end": 245.582}, {"word": "in", "start": 245.622, "end": 245.782}, {"word": "Deutschland", "start": 245.822, "end": 246.563}, {"word": "wünschen.", "start": 246.603, "end": 248.163}, {"word": "Wenn", "start": 248.183, "end": 248.504}, {"word": "Ihr", "start": 248.564, "end": 248.784}, {"word": "mal", "start": 248.904, "end": 249.184}, {"word": "nachschaut,", "start": 249.244, "end": 250.404}, {"word": "werdet", "start": 250.424, "end": 250.845}, {"word": "Ihr", "start": 250.905, "end": 251.125}, {"word": "sehen,", "start": 251.185, "end": 252.005}, {"word": "dass", "start": 252.025, "end": 252.385}, {"word": "manche", "start": 252.425, "end": 252.946}, {"word": "dieser", "start": 252.966, "end": 253.326}, {"word": "Uhren", "start": 253.406, "end": 254.106}, {"word": "150.000", "start": 254.286, "end": 256.587}, {"word": "Euro", "start": 256.648, "end": 257.088}, {"word": "kosten.", "start": 257.128, "end": 257.488}, {"word": "Würdet", "start": 259.393, "end": 259.853}, {"word": "Ihr", "start": 259.934, "end": 260.414}, {"word": "so", "start": 260.454, "end": 260.714}, {"word": "viel", "start": 260.754, "end": 261.094}, {"word": "Geld", "start": 261.134, "end": 261.775}, {"word": "für", "start": 261.815, "end": 262.075}, {"word": "eine", "start": 262.135, "end": 262.435}, {"word": "Uhr", "start": 262.535, "end": 262.895}, {"word": "ausgeben?", "start": 262.975, "end": 264.817}, {"word": "Viele", "start": 264.837, "end": 265.217}, {"word": "Menschen", "start": 265.257, "end": 265.777}, {"word": "tun", "start": 265.817, "end": 266.137}, {"word": "das,", "start": 266.177, "end": 266.898}, {"word": "denn", "start": 266.918, "end": 267.238}, {"word": "eine", "start": 267.278, "end": 267.558}, {"word": "Uhr", "start": 267.658, "end": 268.199}, {"word": "ist", "start": 268.259, "end": 268.619}, {"word": "und", "start": 268.659, "end": 268.979}, {"word": "bleibt", "start": 269.039, "end": 269.599}, {"word": "ein", "start": 269.64, "end": 269.86}, {"word": "Statussymbol.", "start": 269.94, "end": 272.101}, {"word": "Ob", "start": 272.161, "end": 272.381}, {"word": "es", "start": 272.441, "end": 272.741}, {"word": "die", "start": 272.781, "end": 272.982}, {"word": "berühmte", "start": 273.022, "end": 273.862}, {"word": "Rolex", "start": 273.922, "end": 274.563}, {"word": "ist", "start": 274.643, "end": 275.443}, {"word": "oder", "start": 275.483, "end": 276.023}, {"word": "eine", "start": 276.063, "end": 276.344}, {"word": "Glashütte-Uhr,", "start": 276.384, "end": 278.165}, {"word": "das", "start": 278.205, "end": 278.505}, {"word": "könnte", "start": 278.545, "end": 279.165}, {"word": "viel", "start": 279.205, "end": 279.606}, {"word": "über", "start": 279.666, "end": 279.926}, {"word": "den", "start": 279.966, "end": 280.186}, {"word": "Träger", "start": 280.246, "end": 280.826}, {"word": "aussagen,", "start": 280.886, "end": 281.787}, {"word": "oder?", "start": 281.847, "end": 282.087}, {"word": "Egal", "start": 283.608, "end": 284.089}, {"word": "wie", "start": 284.129, "end": 284.329}, {"word": "teuer", "start": 284.409, "end": 284.849}, {"word": "eine", "start": 284.91, "end": 285.19}, {"word": "Uhr", "start": 285.29, "end": 285.63}, {"word": "aber", "start": 285.67, "end": 286.031}, {"word": "ist,", "start": 286.091, "end": 286.871}, {"word": "eines", "start": 286.931, "end": 287.432}, {"word": "kann", "start": 287.472, "end": 287.732}, {"word": "sie", "start": 287.752, "end": 287.912}, {"word": "nicht.", "start": 287.972, "end": 288.913}, {"word": "Sie", "start": 288.953, "end": 289.094}, {"word": "kann", "start": 289.134, "end": 289.374}, {"word": "uns", "start": 289.414, "end": 289.694}, {"word": "nicht", "start": 289.734, "end": 290.114}, {"word": "mehr", "start": 290.134, "end": 290.455}, {"word": "Zeit", "start": 290.495, "end": 290.815}, {"word": "verschaffen", "start": 290.855, "end": 291.896}, {"word": "für", "start": 291.916, "end": 292.216}, {"word": "all", "start": 292.257, "end": 292.497}, {"word": "die", "start": 292.517, "end": 292.697}, {"word": "Dinge,", "start": 292.737, "end": 293.398}, {"word": "die", "start": 293.438, "end": 293.558}, {"word": "wir", "start": 293.598, "end": 293.798}, {"word": "noch", "start": 293.838, "end": 294.098}, {"word": "gerne", "start": 294.138, "end": 294.619}, {"word": "in", "start": 294.659, "end": 294.839}, {"word": "unserem", "start": 294.899, "end": 295.4}, {"word": "Leben", "start": 295.44, "end": 296.04}, {"word": "tun", "start": 296.08, "end": 296.4}, {"word": "würden.", "start": 296.441, "end": 296.681}], "duration": 309.706875}